register_file.v
`timescale 1ns/1ps

/*
Name: Abdulrahmaan Lawal
R-Number: R111914753
Assignment: Project X (Final CPU)
*/

module register_file (load_enable, DA, BusA, BusB, BusD, Aselcect, Bselect, RL);
    // Write control signals
    input load_enable;           // Enable writing to registers
    input [4:0] DA;              // Destination address (which register to write)
    input [31:0] BusD;           // Data to write
    input RL;                    // Read/Load control signal
    
    // Read control signals
    input [4:0] Aselcect;        // Address for BusA read port
    input [4:0] Bselect;         // Address for BusB read port
    
    // Read outputs
    output reg [31:0] BusA;      // Data from register at Aselect
    output reg [31:0] BusB;      // Data from register at Bselect
    
    reg [31:0] registers [31:0]; // 32 registers of 32 bits each

    // Synchronous write: writes happen when load_enable and RL are both high
    always @(load_enable) begin
        if (RL == 1 && load_enable == 1)
            registers[DA] <= BusD;
    end

    // Combinational read: reads are immediate, no clock delay
    always @(*) begin
        BusA = registers[Aselcect];
        BusB = registers[Bselect];
    end

endmodule

register_file_tb.v
/*
Name: Abdulrahmaan Lawal
R-Number: R11914753
Assignment: Project 2
*/

`timescale 1ns/1ps

module register_file_tb ();
    reg load_enable;
    reg [4:0] DA;
    wire [31:0] BusA;
    wire [31:0] BusB;
    reg [31:0] BusD;
    reg [4:0] Aselcect;
    reg [4:0] Bselect;
    reg RL;
    integer i; 

register_file uut(
    .load_enable(load_enable),
    .DA(DA),
    .BusA(BusA),
    .BusB(BusB),
    .BusD(BusD),
    .Aselcect(Aselcect),
    .Bselect(Bselect),
    .RL(RL)
); 
    
    initial begin
        load_enable = 0; DA = 5'b00000; BusD = 32'h00000000; Aselcect = 5'b00000; Bselect = 5'b00000; RL = 0;
        #20;
        
        // Test writing to registers
        for (i = 0; i < 32; i = i + 1) begin
            DA = i; BusD = 32'h00000001 << i; RL = 1; load_enable = 1;
            #20;
            load_enable = 0; RL = 0; // Disable writing after each write
            #20;

        end
        
        // Test reading from registers
        load_enable = 0; RL = 0;  // Turn off writes
        for (i = 0; i < 32; i = i + 1) begin
            Aselcect = i; Bselect = (31 - i);
            #20;
        end
        
        $finish;
    end
endmodule

register_file_output.vcd
$date
	Fri Mar 13 20:48:07 2026
$end
$version
	Icarus Verilog
$end
$timescale
	1ps
$end
$scope module register_file_tb $end
$var wire 32 ! BusB [31:0] $end
$var wire 32 " BusA [31:0] $end
$var reg 5 # Aselcect [4:0] $end
$var reg 5 $ Bselect [4:0] $end
$var reg 32 % BusD [31:0] $end
$var reg 5 & DA [4:0] $end
$var reg 1 ' RL $end
$var reg 1 ( load_enable $end
$var integer 32 ) i [31:0] $end
$scope module uut $end
$var wire 5 * Aselcect [4:0] $end
$var wire 5 + Bselect [4:0] $end
$var wire 32 , BusD [31:0] $end
$var wire 5 - DA [4:0] $end
$var wire 1 ' RL $end
$var wire 1 ( load_enable $end
$var reg 32 . BusA [31:0] $end
$var reg 32 / BusB [31:0] $end
$upscope $end
$upscope $end
$enddefinitions $end
$comment Show the parameter values. $end
$dumpall
$end
#0
$dumpvars
bx /
bx .
b0 -
b0 ,
b0 +
b0 *
bx )
0(
0'
b0 &
b0 %
b0 $
b0 #
bx "
bx !
$end
#20000
b1 !
b1 /
b1 "
b1 .
1(
1'
b1 %
b1 ,
b0 )
#40000
0'
0(
#60000
1(
1'
b10 %
b10 ,
b1 &
b1 -
b1 )
#80000
0'
0(
#100000
1(
1'
b100 %
b100 ,
b10 &
b10 -
b10 )
#120000
0'
0(
#140000
1(
1'
b1000 %
b1000 ,
b11 &
b11 -
b11 )
#160000
0'
0(
#180000
1(
1'
b10000 %
b10000 ,
b100 &
b100 -
b100 )
#200000
0'
0(
#220000
1(
1'
b100000 %
b100000 ,
b101 &
b101 -
b101 )
#240000
0'
0(
#260000
1(
1'
b1000000 %
b1000000 ,
b110 &
b110 -
b110 )
#280000
0'
0(
#300000
1(
1'
b10000000 %
b10000000 ,
b111 &
b111 -
b111 )
#320000
0'
0(
#340000
1(
1'
b100000000 %
b100000000 ,
b1000 &
b1000 -
b1000 )
#360000
0'
0(
#380000
1(
1'
b1000000000 %
b1000000000 ,
b1001 &
b1001 -
b1001 )
#400000
0'
0(
#420000
1(
1'
b10000000000 %
b10000000000 ,
b1010 &
b1010 -
b1010 )
#440000
0'
0(
#460000
1(
1'
b100000000000 %
b100000000000 ,
b1011 &
b1011 -
b1011 )
#480000
0'
0(
#500000
1(
1'
b1000000000000 %
b1000000000000 ,
b1100 &
b1100 -
b1100 )
#520000
0'
0(
#540000
1(
1'
b10000000000000 %
b10000000000000 ,
b1101 &
b1101 -
b1101 )
#560000
0'
0(
#580000
1(
1'
b100000000000000 %
b100000000000000 ,
b1110 &
b1110 -
b1110 )
#600000
0'
0(
#620000
1(
1'
b1000000000000000 %
b1000000000000000 ,
b1111 &
b1111 -
b1111 )
#640000
0'
0(
#660000
1(
1'
b10000000000000000 %
b10000000000000000 ,
b10000 &
b10000 -
b10000 )
#680000
0'
0(
#700000
1(
1'
b100000000000000000 %
b100000000000000000 ,
b10001 &
b10001 -
b10001 )
#720000
0'
0(
#740000
1(
1'
b1000000000000000000 %
b1000000000000000000 ,
b10010 &
b10010 -
b10010 )
#760000
0'
0(
#780000
1(
1'
b10000000000000000000 %
b10000000000000000000 ,
b10011 &
b10011 -
b10011 )
#800000
0'
0(
#820000
1(
1'
b100000000000000000000 %
b100000000000000000000 ,
b10100 &
b10100 -
b10100 )
#840000
0'
0(
#860000
1(
1'
b1000000000000000000000 %
b1000000000000000000000 ,
b10101 &
b10101 -
b10101 )
#880000
0'
0(
#900000
1(
1'
b10000000000000000000000 %
b10000000000000000000000 ,
b10110 &
b10110 -
b10110 )
#920000
0'
0(
#940000
1(
1'
b100000000000000000000000 %
b100000000000000000000000 ,
b10111 &
b10111 -
b10111 )
#960000
0'
0(
#980000
1(
1'
b1000000000000000000000000 %
b1000000000000000000000000 ,
b11000 &
b11000 -
b11000 )
#1000000
0'
0(
#1020000
1(
1'
b10000000000000000000000000 %
b10000000000000000000000000 ,
b11001 &
b11001 -
b11001 )
#1040000
0'
0(
#1060000
1(
1'
b100000000000000000000000000 %
b100000000000000000000000000 ,
b11010 &
b11010 -
b11010 )
#1080000
0'
0(
#1100000
1(
1'
b1000000000000000000000000000 %
b1000000000000000000000000000 ,
b11011 &
b11011 -
b11011 )
#1120000
0'
0(
#1140000
1(
1'
b10000000000000000000000000000 %
b10000000000000000000000000000 ,
b11100 &
b11100 -
b11100 )
#1160000
0'
0(
#1180000
1(
1'
b100000000000000000000000000000 %
b100000000000000000000000000000 ,
b11101 &
b11101 -
b11101 )
#1200000
0'
0(
#1220000
1(
1'
b1000000000000000000000000000000 %
b1000000000000000000000000000000 ,
b11110 &
b11110 -
b11110 )
#1240000
0'
0(
#1260000
1(
1'
b10000000000000000000000000000000 %
b10000000000000000000000000000000 ,
b11111 &
b11111 -
b11111 )
#1280000
0'
0(
#1300000
b10000000000000000000000000000000 !
b10000000000000000000000000000000 /
b11111 $
b11111 +
b0 )
#1320000
b1000000000000000000000000000000 !
b1000000000000000000000000000000 /
b10 "
b10 .
b11110 $
b11110 +
b1 #
b1 *
b1 )
#1340000
b100000000000000000000000000000 !
b100000000000000000000000000000 /
b100 "
b100 .
b11101 $
b11101 +
b10 #
b10 *
b10 )
#1360000
b10000000000000000000000000000 !
b10000000000000000000000000000 /
b1000 "
b1000 .
b11100 $
b11100 +
b11 #
b11 *
b11 )
#1380000
b1000000000000000000000000000 !
b1000000000000000000000000000 /
b10000 "
b10000 .
b11011 $
b11011 +
b100 #
b100 *
b100 )
#1400000
b100000000000000000000000000 !
b100000000000000000000000000 /
b100000 "
b100000 .
b11010 $
b11010 +
b101 #
b101 *
b101 )
#1420000
b10000000000000000000000000 !
b10000000000000000000000000 /
b1000000 "
b1000000 .
b11001 $
b11001 +
b110 #
b110 *
b110 )
#1440000
b1000000000000000000000000 !
b1000000000000000000000000 /
b10000000 "
b10000000 .
b11000 $
b11000 +
b111 #
b111 *
b111 )
#1460000
b100000000000000000000000 !
b100000000000000000000000 /
b100000000 "
b100000000 .
b10111 $
b10111 +
b1000 #
b1000 *
b1000 )
#1480000
b10000000000000000000000 !
b10000000000000000000000 /
b1000000000 "
b1000000000 .
b10110 $
b10110 +
b1001 #
b1001 *
b1001 )
#1500000
b1000000000000000000000 !
b1000000000000000000000 /
b10000000000 "
b10000000000 .
b10101 $
b10101 +
b1010 #
b1010 *
b1010 )
#1520000
b100000000000000000000 !
b100000000000000000000 /
b100000000000 "
b100000000000 .
b10100 $
b10100 +
b1011 #
b1011 *
b1011 )
#1540000
b10000000000000000000 !
b10000000000000000000 /
b1000000000000 "
b1000000000000 .
b10011 $
b10011 +
b1100 #
b1100 *
b1100 )
#1560000
b1000000000000000000 !
b1000000000000000000 /
b10000000000000 "
b10000000000000 .
b10010 $
b10010 +
b1101 #
b1101 *
b1101 )
#1580000
b100000000000000000 !
b100000000000000000 /
b100000000000000 "
b100000000000000 .
b10001 $
b10001 +
b1110 #
b1110 *
b1110 )
#1600000
b10000000000000000 !
b10000000000000000 /
b1000000000000000 "
b1000000000000000 .
b10000 $
b10000 +
b1111 #
b1111 *
b1111 )
#1620000
b1000000000000000 !
b1000000000000000 /
b10000000000000000 "
b10000000000000000 .
b1111 $
b1111 +
b10000 #
b10000 *
b10000 )
#1640000
b100000000000000 !
b100000000000000 /
b100000000000000000 "
b100000000000000000 .
b1110 $
b1110 +
b10001 #
b10001 *
b10001 )
#1660000
b10000000000000 !
b10000000000000 /
b1000000000000000000 "
b1000000000000000000 .
b1101 $
b1101 +
b10010 #
b10010 *
b10010 )
#1680000
b1000000000000 !
b1000000000000 /
b10000000000000000000 "
b10000000000000000000 .
b1100 $
b1100 +
b10011 #
b10011 *
b10011 )
#1700000
b100000000000 !
b100000000000 /
b100000000000000000000 "
b100000000000000000000 .
b1011 $
b1011 +
b10100 #
b10100 *
b10100 )
#1720000
b10000000000 !
b10000000000 /
b1000000000000000000000 "
b1000000000000000000000 .
b1010 $
b1010 +
b10101 #
b10101 *
b10101 )
#1740000
b1000000000 !
b1000000000 /
b10000000000000000000000 "
b10000000000000000000000 .
b1001 $
b1001 +
b10110 #
b10110 *
b10110 )
#1760000
b100000000 !
b100000000 /
b100000000000000000000000 "
b100000000000000000000000 .
b1000 $
b1000 +
b10111 #
b10111 *
b10111 )
#1780000
b10000000 !
b10000000 /
b1000000000000000000000000 "
b1000000000000000000000000 .
b111 $
b111 +
b11000 #
b11000 *
b11000 )
#1800000
b1000000 !
b1000000 /
b10000000000000000000000000 "
b10000000000000000000000000 .
b110 $
b110 +
b11001 #
b11001 *
b11001 )
#1820000
b100000 !
b100000 /
b100000000000000000000000000 "
b100000000000000000000000000 .
b101 $
b101 +
b11010 #
b11010 *
b11010 )
#1840000
b10000 !
b10000 /
b1000000000000000000000000000 "
b1000000000000000000000000000 .
b100 $
b100 +
b11011 #
b11011 *
b11011 )
#1860000
b1000 !
b1000 /
b10000000000000000000000000000 "
b10000000000000000000000000000 .
b11 $
b11 +
b11100 #
b11100 *
b11100 )
#1880000
b100 !
b100 /
b100000000000000000000000000000 "
b100000000000000000000000000000 .
b10 $
b10 +
b11101 #
b11101 *
b11101 )
#1900000
b10 !
b10 /
b1000000000000000000000000000000 "
b1000000000000000000000000000000 .
b1 $
b1 +
b11110 #
b11110 *
b11110 )
#1920000
b1 !
b1 /
b10000000000000000000000000000000 "
b10000000000000000000000000000000 .
b0 $
b0 +
b11111 #
b11111 *
b11111 )
#1940000
b100000 )
