coinCounterOut/coinCounterOut.v
 `timescale 1ns/1ps

module coinCounterOut (change, outDime, outNickel, outQuarter, rst, clk);
    parameter QUARTER_VALUE =10'D25;
    parameter NICKEL_VALUE =10'D5;
    parameter DIME_VALUE =10'D10;

    input [10:0] change;
    input rst;
    input clk;
    output reg outDime, outNickel, outQuarter;

    reg [10:0] remainingChange;
    reg [10:0] lastchange;

    

    always @(posedge clk or posedge rst) begin
        outDime <= 1'b0;
        outNickel <= 1'b0;
        outQuarter <= 1'b0;
        if (rst == 1'b1) begin
            outDime <= 1'b0;
            outNickel <= 1'b0;
            outQuarter <= 1'b0;
            remainingChange <= 10'D0;
            lastchange <= 10'D0;
        end else begin

            if (remainingChange == 11'd0 && change != lastchange && change > 11'd0) begin
                remainingChange <= change;
                lastchange <= change;
                outDime <= 1'b0;
                outNickel <= 1'b0;
                outQuarter <= 1'b0;
            end

            else if (remainingChange >= QUARTER_VALUE) begin
                outQuarter <= 1'b1;
                remainingChange <= remainingChange - QUARTER_VALUE;

            end else if (remainingChange >= DIME_VALUE) begin
                outDime <= 1'b1;
                remainingChange <= remainingChange - DIME_VALUE;
            end else if (remainingChange >= NICKEL_VALUE) begin
                outNickel <= 1'b1;
                remainingChange <= remainingChange - NICKEL_VALUE;
            end else begin
                outDime <= 0;
                outNickel <= 0;
                outQuarter <= 0;
                
            end
        end
    end
    
endmodule

coinCounterOut/coinCounterOut_tb.v
`timescale 1ns/1ps

module coinCounterOut_tb ();
reg [10:0] change;
reg rst;
reg clk;
wire outDime, outNickel, outQuarter;
coinCounterOut uut (
    .change(change), 
    .outDime(outDime), 
    .outNickel(outNickel), 
    .outQuarter(outQuarter), 
    .rst(rst),
    .clk(clk)
);

initial begin
    clk = 0;
    forever #10 clk = ~clk; // 20ns clock period
end

initial begin
    change = 10'D0; rst = 0;
    $dumpfile("coinCounterOut_output.vcd");
    $dumpvars(0, coinCounterOut_tb);
    rst = 1; 
    #20;

    rst = 0; change = 10'd300;
    #400;
    change = 10'd15;
    #400;
   change = 10'd5;
    #400;
    change = 10'd0;
    #400;

    $finish;
end
    
endmodule

coinCounterOut/coinCounterOut_output.vcd
$date
	Thu Feb 26 19:07:18 2026
$end
$version
	Icarus Verilog
$end
$timescale
	1ps
$end
$scope module coinCounterOut_tb $end
$var wire 1 ! outQuarter $end
$var wire 1 " outNickel $end
$var wire 1 # outDime $end
$var reg 11 $ change [10:0] $end
$var reg 1 % clk $end
$var reg 1 & rst $end
$scope module uut $end
$var wire 11 ' change [10:0] $end
$var wire 1 % clk $end
$var wire 1 & rst $end
$var parameter 10 ( DIME_VALUE $end
$var parameter 10 ) NICKEL_VALUE $end
$var parameter 10 * QUARTER_VALUE $end
$var reg 11 + lastchange [10:0] $end
$var reg 1 # outDime $end
$var reg 1 " outNickel $end
$var reg 1 ! outQuarter $end
$var reg 11 , remainingChange [10:0] $end
$upscope $end
$upscope $end
$enddefinitions $end
$comment Show the parameter values. $end
$dumpall
b11001 *
b101 )
b1010 (
$end
#0
$dumpvars
b0 ,
b0 +
b0 '
1&
0%
b0 $
0#
0"
0!
$end
#10000
1%
#20000
0%
b100101100 $
b100101100 '
0&
#30000
b100101100 +
b100101100 ,
1%
#40000
0%
#50000
b100010011 ,
1!
1%
#60000
0%
#70000
b11111010 ,
1%
#80000
0%
#90000
b11100001 ,
1%
#100000
0%
#110000
b11001000 ,
1%
#120000
0%
#130000
b10101111 ,
1%
#140000
0%
#150000
b10010110 ,
1%
#160000
0%
#170000
b1111101 ,
1%
#180000
0%
#190000
b1100100 ,
1%
#200000
0%
#210000
b1001011 ,
1%
#220000
0%
#230000
b110010 ,
1%
#240000
0%
#250000
b11001 ,
1%
#260000
0%
#270000
b0 ,
1%
#280000
0%
#290000
0!
1%
#300000
0%
#310000
1%
#320000
0%
#330000
1%
#340000
0%
#350000
1%
#360000
0%
#370000
1%
#380000
0%
#390000
1%
#400000
0%
#410000
1%
#420000
0%
b1111 $
b1111 '
#430000
b1111 +
b1111 ,
1%
#440000
0%
#450000
b101 ,
1#
1%
#460000
0%
#470000
b0 ,
1"
1%
#480000
0%
#490000
0"
0#
1%
#500000
0%
#510000
1%
#520000
0%
#530000
1%
#540000
0%
#550000
1%
#560000
0%
#570000
1%
#580000
0%
#590000
1%
#600000
0%
#610000
1%
#620000
0%
#630000
1%
#640000
0%
#650000
1%
#660000
0%
#670000
1%
#680000
0%
#690000
1%
#700000
0%
#710000
1%
#720000
0%
#730000
1%
#740000
0%
#750000
1%
#760000
0%
#770000
1%
#780000
0%
#790000
1%
#800000
0%
#810000
1%
#820000
0%
b101 $
b101 '
#830000
b101 +
b101 ,
1%
#840000
0%
#850000
b0 ,
1"
1%
#860000
0%
#870000
0"
1%
#880000
0%
#890000
1%
#900000
0%
#910000
1%
#920000
0%
#930000
1%
#940000
0%
#950000
1%
#960000
0%
#970000
1%
#980000
0%
#990000
1%
#1000000
0%
#1010000
1%
#1020000
0%
#1030000
1%
#1040000
0%
#1050000
1%
#1060000
0%
#1070000
1%
#1080000
0%
#1090000
1%
#1100000
0%
#1110000
1%
#1120000
0%
#1130000
1%
#1140000
0%
#1150000
1%
#1160000
0%
#1170000
1%
#1180000
0%
#1190000
1%
#1200000
0%
#1210000
1%
#1220000
0%
b0 $
b0 '
