coinCounterOut/coinCounterOut.v
 `timescale 1ns/1ps

module coinCounterOut (change, outDime, outNickel, outQuarter, rst, clk);
    parameter QUARTER_VALUE =10'D25;
    parameter NICKEL_VALUE =10'D5;
    parameter DIME_VALUE =10'D10;

    input [10:0] change;
    input rst;
    input clk;
    output reg outDime, outNickel, outQuarter;

    reg [10:0] remainingChange;
    reg [10:0] lastchange;

    

    always @(posedge clk or posedge rst) begin
        outDime <= 1'b0;
        outNickel <= 1'b0;
        outQuarter <= 1'b0;
        if (rst == 1'b1) begin
            outDime <= 1'b0;
            outNickel <= 1'b0;
            outQuarter <= 1'b0;
            remainingChange <= 10'D0;
            lastchange <= 10'D0;
        end else begin

            if (remainingChange == 11'd0 && change != lastchange && change > 11'd0) begin
                remainingChange <= change;
                lastchange <= change;
                outDime <= 1'b0;
                outNickel <= 1'b0;
                outQuarter <= 1'b0;
            end

            else if (remainingChange >= QUARTER_VALUE) begin
                outQuarter <= 1'b1;
                remainingChange <= remainingChange - QUARTER_VALUE;

            end else if (remainingChange >= DIME_VALUE) begin
                outDime <= 1'b1;
                remainingChange <= remainingChange - DIME_VALUE;
            end else if (remainingChange >= NICKEL_VALUE) begin
                outNickel <= 1'b1;
                remainingChange <= remainingChange - NICKEL_VALUE;
            end else begin
                outDime <= 0;
                outNickel <= 0;
                outQuarter <= 0;
                
            end
        end
    end
    
endmodule

coinCounterOut/coinCounterOut_tb.v
`timescale 1ns/1ps

module coinCounterOut_tb ();
reg [10:0] change;
reg rst;
reg clk;
wire outDime, outNickel, outQuarter;
coinCounterOut uut (
    .change(change), 
    .outDime(outDime), 
    .outNickel(outNickel), 
    .outQuarter(outQuarter), 
    .rst(rst),
    .clk(clk)
);

initial begin
    clk = 0;
    forever #10 clk = ~clk; // 20ns clock period
end

initial begin
    change = 10'D0; rst = 0;
    $dumpfile("coinCounterOut_output.vcd");
    $dumpvars(0, coinCounterOut_tb);
    rst = 1; 
    #20;

    rst = 0; change = 10'd300;
    #400;
    change = 10'd15;
    #400;
   change = 10'd5;
    #400;
    change = 10'd0;
    #400;

    $finish;
end
    
endmodule

realCoinCounter/coinCounterOut_output.vcd
$date
   Fri Feb 27 01:24:18 2026
$end
$version
  P.20131013
$end
$timescale
  1ps
$end
$scope module coinCounterOut_tb $end
$var wire 1 ! outDime $end
$var wire 1 " outNickel $end
$var wire 1 # outQuarter $end
$var reg 11 $ change [10:0] $end
$var reg 1 % rst $end
$var reg 1 & clk $end
$scope module uut $end
$var wire 1 ' change [10] $end
$var wire 1 ( change [9] $end
$var wire 1 ) change [8] $end
$var wire 1 * change [7] $end
$var wire 1 + change [6] $end
$var wire 1 , change [5] $end
$var wire 1 - change [4] $end
$var wire 1 . change [3] $end
$var wire 1 / change [2] $end
$var wire 1 0 change [1] $end
$var wire 1 1 change [0] $end
$var wire 1 2 rst $end
$var wire 1 3 clk $end
$var reg 1 4 outDime $end
$var reg 1 5 outNickel $end
$var reg 1 6 outQuarter $end
$var reg 11 7 remainingChange [10:0] $end
$var reg 11 8 lastchange [10:0] $end
$upscope $end
$upscope $end
$enddefinitions $end
#0
$dumpvars
0!
0.
00
01
0/
0"
0#
0-
0,
0+
0*
0)
0(
0'
03
b0 $
1%
0&
04
05
06
b0 7
b0 8
12
$end
#10000
13
1&
#20000
1.
1/
1,
1)
03
b100101100 $
0%
0&
02
#30000
13
1&
b100101100 7
b100101100 8
#40000
03
0&
#50000
1#
13
1&
16
b100010011 7
#60000
03
0&
#70000
13
1&
b11111010 7
#80000
03
0&
#90000
13
1&
b11100001 7
#100000
03
0&
#110000
13
1&
b11001000 7
#120000
03
0&
#130000
13
1&
b10101111 7
#140000
03
0&
#150000
13
1&
b10010110 7
#160000
03
0&
#170000
13
1&
b1111101 7
#180000
03
0&
#190000
13
1&
b1100100 7
#200000
03
0&
#210000
13
1&
b1001011 7
#220000
03
0&
#230000
13
1&
b110010 7
#240000
03
0&
#250000
13
1&
b11001 7
#260000
03
0&
#270000
13
1&
b0 7
#280000
03
0&
#290000
0#
13
1&
06
#300000
03
0&
#310000
13
1&
#320000
03
0&
#330000
13
1&
#340000
03
0&
#350000
13
1&
#360000
03
0&
#370000
13
1&
#380000
03
0&
#390000
13
1&
#400000
03
0&
#410000
13
1&
#420000
10
11
0,
0)
03
b1111 $
0&
#430000
13
1&
b1111 7
b1111 8
#440000
03
0&
#450000
1!
13
1&
14
b101 7
#460000
03
0&
#470000
1"
13
1&
15
b0 7
#480000
03
0&
#490000
0!
0"
13
1&
04
05
#500000
03
0&
#510000
13
1&
#520000
03
0&
#530000
13
1&
#540000
03
0&
#550000
13
1&
#560000
03
0&
#570000
13
1&
#580000
03
0&
#590000
13
1&
#600000
03
0&
#610000
13
1&
#620000
03
0&
#630000
13
1&
#640000
03
0&
#650000
13
1&
#660000
03
0&
#670000
13
1&
#680000
03
0&
#690000
13
1&
#700000
03
0&
#710000
13
1&
#720000
03
0&
#730000
13
1&
#740000
03
0&
#750000
13
1&
#760000
03
0&
#770000
13
1&
#780000
03
0&
#790000
13
1&
#800000
03
0&
#810000
13
1&
#820000
0.
00
03
b101 $
0&
#830000
13
1&
b101 7
b101 8
#840000
03
0&
#850000
1"
13
1&
15
b0 7
#860000
03
0&
#870000
0"
13
1&
05
